django_task_mq/__init__.py
django_task_mq-1.2.3.dist-info/LICENSE
django_task_mq-1.2.3.dist-info/METADATA
django_task_mq-1.2.3.dist-info/WHEEL
django_task_mq-1.2.3.dist-info/top_level.txt
django_task_mq-1.2.3.dist-info/RECORD
